repenseai/error/exceptions.py
repenseai/genai/agent.py
repenseai/genai/api/anthropic.py
repenseai/genai/api/aws.py
repenseai/genai/api/cohere.py
repenseai/genai/api/deepseek.py
repenseai/genai/api/google.py
repenseai/genai/api/groq.py
repenseai/genai/api/maritaca.py
repenseai/genai/api/mistral.py
repenseai/genai/api/nvidia.py
repenseai/genai/api/openai.py
repenseai/genai/api/perplexity.py
repenseai/genai/api/sambanova.py
repenseai/genai/api/stability.py
repenseai/genai/api/together.py
repenseai/genai/api/x.py
repenseai/genai/benchmark/core/base_benchmark.py
repenseai/genai/benchmark/core/base_evaluator.py
repenseai/genai/benchmark/core/base_provider.py
repenseai/genai/benchmark/core/base_test.py
repenseai/genai/benchmark/evaluators/json_evaluator.py
repenseai/genai/benchmark/evaluators/open_evaluator.py
repenseai/genai/benchmark/evaluators/option_evaluator.py
repenseai/genai/benchmark/evaluators/simple_evaluator.py
repenseai/genai/benchmark/tests/json_extraction.py
repenseai/genai/benchmark/tests/open_question.py
repenseai/genai/benchmark/tests/option_question.py
repenseai/genai/benchmark/tests/simple_output.py
repenseai/genai/mcp/server.py
repenseai/genai/providers.py
repenseai/genai/tasks/api.py
repenseai/genai/tasks/base.py
repenseai/genai/tasks/conditional.py
repenseai/genai/tasks/function.py
repenseai/genai/tasks/parallel.py
repenseai/genai/tasks/workflow.py
repenseai/secrets/aws.py
repenseai/secrets/base.py
repenseai/utils/agent.py
repenseai/utils/audio.py
repenseai/utils/image.py
repenseai/utils/logs.py
repenseai/utils/text.py
repenseai-4.0.14.dist-info/LICENSE
repenseai-4.0.14.dist-info/METADATA
repenseai-4.0.14.dist-info/WHEEL
repenseai-4.0.14.dist-info/RECORD
