Metadata-Version: 2.1
Name: repenseai
Version: 4.0.14
Summary: Repense package to support AI solutions
Author: Samuel Baptista
Author-email: samuel.baptista@repense.ai
Requires-Python: >=3.12,<4.0
Classifier: Programming Language :: Python :: 3
Classifier: Programming Language :: Python :: 3.12
Requires-Dist: anthropic (>=0.47.1,<0.48.0)
Requires-Dist: boto3 (>=1.36.24,<2.0.0)
Requires-Dist: cohere (>=5.8.1,<6.0.0)
Requires-Dist: google-genai (>=1.2.0,<2.0.0)
Requires-Dist: groq (>=0.18.0,<0.19.0)
Requires-Dist: jsonschema (>=4.23.0,<5.0.0)
Requires-Dist: matplotlib (>=3.10.0,<4.0.0)
Requires-Dist: mcp (>=1.5.0,<2.0.0)
Requires-Dist: mistralai (>=1.0.2,<2.0.0)
Requires-Dist: nltk (>=3.9.1,<4.0.0)
Requires-Dist: openai (>=1.42.0,<2.0.0)
Requires-Dist: pandas (>=2.2.3,<3.0.0)
Requires-Dist: pillow (>=10.4.0,<11.0.0)
Requires-Dist: python-dotenv (>=1.0.1,<2.0.0)
Requires-Dist: rouge-score (>=0.1.2,<0.2.0)
Requires-Dist: scikit-learn (>=1.6.0,<2.0.0)
Requires-Dist: setuptools (>=75.1.0,<76.0.0)
Requires-Dist: together (>=1.3.4,<2.0.0)
Requires-Dist: unidecode (>=1.3.8,<2.0.0)
